advanced_global_optimizers/Problem.py
advanced_global_optimizers/__init__.py
advanced_global_optimizers/constrained_solvers/DTPSO.py
advanced_global_optimizers/constrained_solvers/DTPSO_base.py
advanced_global_optimizers/constrained_solvers/GATDX_base.py
advanced_global_optimizers/constrained_solvers/GA_TDX.py
advanced_global_optimizers/constrained_solvers/HECODE_base.py
advanced_global_optimizers/constrained_solvers/HECO_DE.py
advanced_global_optimizers/constrained_solvers/__init__.py
advanced_global_optimizers/unconstrained_solvers/AMCDE.py
advanced_global_optimizers/unconstrained_solvers/AMCDE_base.py
advanced_global_optimizers/unconstrained_solvers/BasicDE.py
advanced_global_optimizers/unconstrained_solvers/DE_base.py
advanced_global_optimizers/unconstrained_solvers/GLPSO.py
advanced_global_optimizers/unconstrained_solvers/GLPSO_base.py
advanced_global_optimizers/unconstrained_solvers/MadDE.py
advanced_global_optimizers/unconstrained_solvers/MadDE_base.py
advanced_global_optimizers/unconstrained_solvers/__init__.py
advanced_global_optimizers/unconstrained_solvers/sDMS_PSO.py
advanced_global_optimizers/unconstrained_solvers/sDMS_base.py
advanced_global_optimizers-0.0.3.dist-info/LICENSE
advanced_global_optimizers-0.0.3.dist-info/METADATA
advanced_global_optimizers-0.0.3.dist-info/WHEEL
advanced_global_optimizers-0.0.3.dist-info/top_level.txt
advanced_global_optimizers-0.0.3.dist-info/RECORD
