Metadata-Version: 2.1
Name: advanced_global_optimizers
Version: 0.0.3
Summary: A package that integrates many advanced global optimizers
Author: Anonymous authors
Classifier: Programming Language :: Python :: 3
Classifier: License :: OSI Approved :: MIT License
Classifier: Operating System :: OS Independent
Requires-Python: >=3.8
License-File: LICENSE
Requires-Dist: numpy
Requires-Dist: scipy
Requires-Dist: jax
Requires-Dist: evosax
Requires-Dist: pypop7
